{
  "scriptId": 2800040016,
  "allowTick": false,
  "allowStartOnTravelPole": false,
  "startType": "ByEnterStartShape",
  "endType": "ByExitStartShape",
  "refGameId": null,
  "exitBuffer": 0.0,
  "modules": {},
  "isEmbedded": true,
  "refActionMapPath": null,
  "actionMap": {
    "paramBlackboard": {
      "value": []
    },
    "dataMap": {
      "headerList": [
        {
          "$type": "Beyond.Gameplay.Actions.ScriptEvent.OnScriptStart, Gameplay.Beyond",
          "_ID": 0,
          "_nextID": 1,
          "_targetScript": null,
          "_validate": {
            "constValue": true
          },
          "_uid": "73fb65e7"
        },
        {
          "$type": "Beyond.Gameplay.Actions.ScriptEvent.OnScriptEnd, Gameplay.Beyond",
          "_ID": 8,
          "_nextID": 3,
          "_targetScript": null,
          "_validate": {
            "constValue": true
          },
          "_reasonFilter": null,
          "_uid": "354d4996"
        }
      ],
      "actionList": [
        {
          "$type": "Beyond.Gameplay.Actions.Split, Gameplay.Beyond",
          "_ID": 1,
          "_idList": [
            7,
            2
          ],
          "_uid": "44b42109"
        },
        {
          "$type": "Beyond.Gameplay.Actions.Play3DRadio, Gameplay.Beyond",
          "_ID": 7,
          "_radioId": {
            "constValue": "radio_c1m1_9"
          },
          "_fromBegin": {
            "constValue": true
          },
          "_index": {
            "constValue": -1
          },
          "_entityPtr": {
            "constValue": {
              "logicId": 2800040020
            }
          },
          "_uid": "2570b850",
          "useCurrentScope": true
        },
        {
          "$type": "Beyond.Gameplay.Actions.LevelCameraLookAt, Gameplay.Beyond",
          "_ID": 2,
          "_nextID": 6,
          "lookAt1Type": {
            "constValue": "Entity"
          },
          "lookAt1": {
            "constValue": {
              "logicId": 2800040034
            }
          },
          "position1": {
            "constValue": {
              "x": -353.6901,
              "y": 173.0,
              "z": 543.9316
            }
          },
          "direction1": null,
          "rotation1": null,
          "lookAt2Type": {
            "constValue": "Entity"
          },
          "lookAt2": {
            "constValue": {
              "logicId": 0
            }
          },
          "position2": null,
          "direction2": null,
          "rotation2": null,
          "alpha": {
            "constValue": 0.0
          },
          "horizontalBaseAngle": {
            "constValue": 0.0
          },
          "verticalBaseValue": {
            "constValue": 0.5
          },
          "horizontalSpeedFactor": {
            "constValue": 0.05
          },
          "verticalSpeedFactor": {
            "constValue": 0.05
          },
          "noInputDampingTime": {
            "constValue": 1.0
          },
          "blendStyle": {
            "constValue": "EaseInOut"
          },
          "blendTime": {
            "constValue": 1.0
          },
          "useInitialParam": {
            "constValue": false
          },
          "initParam": {
            "constValue": {
              "applyHorizontalAngle": false,
              "horizontalAngleRelativeToCharacter": false,
              "horizontalAngle": 0.0,
              "applyVerticalValue": false,
              "verticalValue": 0.0,
              "applyZoomScale": false,
              "zoomScale": 0.0
            }
          },
          "useExitParam": {
            "constValue": false
          },
          "exitParam": {
            "constValue": {
              "applyHorizontalAngle": false,
              "horizontalAngleRelativeToCharacter": false,
              "horizontalAngle": 0.0,
              "applyVerticalValue": false,
              "verticalValue": 0.0,
              "applyZoomScale": false,
              "zoomScale": 0.0
            }
          },
          "controlState": {
            "path": "$2@controlState"
          },
          "controlStateId": {
            "path": "$2@controlStateId"
          },
          "_uid": "ad7eae3f",
          "useCurrentScope": true
        },
        {
          "$type": "Beyond.Gameplay.Actions.AddDelayTimer, Gameplay.Beyond",
          "_ID": 6,
          "_nextID": 3,
          "_seconds": {
            "constValue": 2.5
          },
          "_timerId": {
            "path": "$6@_timerId"
          },
          "_onBreakID": 3,
          "_uid": "7304fc57"
        },
        {
          "$type": "Beyond.Gameplay.Actions.RemoveCameraControlState, Gameplay.Beyond",
          "_ID": 3,
          "_nextID": 4,
          "_controlState": {
            "paramSource": 100,
            "path": "$2@controlState",
            "constValue": null
          },
          "_controlStateId": {
            "constValue": 0
          },
          "_overrideBlend": {
            "constValue": true
          },
          "_blendStyle": {
            "constValue": "EaseInOut"
          },
          "_blendTime": {
            "constValue": 1.0
          },
          "_uid": "39bab211",
          "useCurrentScope": true
        },
        {
          "$type": "Beyond.Gameplay.Actions.CallServer, Gameplay.Beyond",
          "_ID": 4,
          "_eventName": {
            "constValue": "#37df9999"
          },
          "_eventArgsPtr": {
            "constValue": {
              "key": "event_args"
            }
          },
          "_uid": "37df9999",
          "useCurrentScope": true
        }
      ],
      "getterList": []
    }
  },
  "resetModeWhenActive": "ResetAllWhenNotDone",
  "resetModeWhenEnd": "None",
  "activeShapeList": [
    {
      "type": "BOX",
      "offset": {
        "x": -312.5,
        "y": 168.03537,
        "z": 520.0547
      },
      "eulerAngles": {
        "x": 0.0,
        "y": 0.0,
        "z": 0.0
      },
      "size": {
        "x": 168.0,
        "y": 160.0,
        "z": 230.0
      },
      "radius": 0.0
    },
    {
      "type": "SPHERE",
      "offset": {
        "x": -312.5,
        "y": 170.71536,
        "z": 520.05475
      },
      "eulerAngles": {
        "x": 0.0,
        "y": 0.0,
        "z": 0.0
      },
      "size": {
        "x": 0.0,
        "y": 0.0,
        "z": 0.0
      },
      "radius": 75.0
    }
  ],
  "startShapeList": [
    {
      "type": "BOX",
      "offset": {
        "x": -312.5,
        "y": 168.03537,
        "z": 520.0547
      },
      "eulerAngles": {
        "x": 0.0,
        "y": 0.0,
        "z": 0.0
      },
      "size": {
        "x": 18.0,
        "y": 10.0,
        "z": 80.0
      },
      "radius": 15.0
    }
  ],
  "properties": [],
  "propertyIdToKeyMap": {}
}