{
  "sceneId": "dung01_sdg005",
  "levelIdNum": 143,
  "specificData": null,
  "blackbox": null,
  "guideHints": [],
  "enemies": [],
  "interactives": [],
  "interactiveLockData": [],
  "factoryRegions": [],
  "factoryMines": [],
  "npcs": [],
  "npcClusters": [],
  "levelScripts": null,
  "levelScriptDataPathDict": {
    "14300000001": "LevelScriptData/dung01_sdg005/14300000001.json"
  },
  "patrols": [],
  "npcAttractSets": [],
  "enemyAttractSets": [],
  "missionAreas": [],
  "taskAreas": [],
  "enemyGroup": [],
  "cameraPoses": [],
  "focusPoints": [],
  "splines": [],
  "airWalls": [],
  "environmentVolumes": [],
  "spawners": [],
  "worldWayPointSets": [],
  "towerWayPointSets": [],
  "waterVolumes": [],
  "levelUIs": [],
  "aiTransData": [],
  "attractLists": [],
  "safeZone": {
    "boxes": []
  },
  "factoryPredefineData": {
    "powerGates": []
  },
  "predefinedParams": [],
  "functionArea": {
    "ranges": [],
    "baseData": [],
    "repatriateZoneData": [],
    "cameraVolumeData": [],
    "radioTriggerZoneData": [],
    "cameraLookAtData": [],
    "cameraAddControlStateData": [],
    "ambienceCameraData": [],
    "storySafeZones": [],
    "sceneToast": [],
    "blockAIBarkData": [],
    "isolateEntityZoneData": [],
    "functionAreaConditionData": []
  },
  "doodadGroup": []
}