{
  "scriptId": 3500150012,
  "allowTick": false,
  "allowStartOnTravelPole": false,
  "startType": "ByEnterStartShape",
  "endType": "ByExitStartShape",
  "refGameId": null,
  "exitBuffer": 0.0,
  "modules": {},
  "isEmbedded": true,
  "refActionMapPath": null,
  "actionMap": {
    "paramBlackboard": {
      "value": []
    },
    "dataMap": {
      "headerList": [
        {
          "$type": "Beyond.Gameplay.Actions.ScriptEvent.OnScriptStart, Gameplay.Beyond",
          "_ID": 12,
          "_nextID": 5,
          "_targetScript": null,
          "_validate": {
            "paramSource": -1,
            "constValue": true,
            "idRef": 11
          },
          "_uid": "8f9ed936"
        },
        {
          "$type": "Beyond.Gameplay.Actions.ScriptEvent.OnScriptStart, Gameplay.Beyond",
          "_ID": 26,
          "_nextID": 18,
          "_targetScript": null,
          "_validate": {
            "paramSource": -1,
            "constValue": true,
            "idRef": 25
          },
          "_uid": "6cf23715"
        },
        {
          "$type": "Beyond.Gameplay.Actions.ScriptEvent.OnScriptStart, Gameplay.Beyond",
          "_ID": 37,
          "_nextID": 32,
          "_targetScript": null,
          "_validate": {
            "paramSource": -1,
            "constValue": true,
            "idRef": 36
          },
          "_uid": "983a95ee"
        },
        {
          "$type": "Beyond.Gameplay.Actions.ScriptEvent.OnCustomEvent, Gameplay.Beyond",
          "_ID": 4,
          "_nextID": 5,
          "_targetScript": null,
          "_validate": {
            "constValue": true
          },
          "_eventKey": {
            "constValue": "#48fe145c"
          },
          "_eventArgsPtr": null,
          "_uid": "48fe145c"
        },
        {
          "$type": "Beyond.Gameplay.Actions.ScriptEvent.OnCustomEvent, Gameplay.Beyond",
          "_ID": 17,
          "_nextID": 18,
          "_targetScript": null,
          "_validate": {
            "constValue": true
          },
          "_eventKey": {
            "constValue": "#7942233f"
          },
          "_eventArgsPtr": null,
          "_uid": "7942233f"
        },
        {
          "$type": "Beyond.Gameplay.Actions.ScriptEvent.OnCustomEvent, Gameplay.Beyond",
          "_ID": 31,
          "_nextID": 32,
          "_targetScript": null,
          "_validate": {
            "constValue": true
          },
          "_eventKey": {
            "constValue": "#093020a9"
          },
          "_eventArgsPtr": null,
          "_uid": "093020a9"
        }
      ],
      "actionList": [
        {
          "$type": "Beyond.Gameplay.Actions.CreateMissionNpc, Gameplay.Beyond",
          "_ID": 5,
          "_nextID": 6,
          "_levelId": {
            "constValue": "map01_lv006"
          },
          "_npcIdList": {
            "constValue": [
              "npc_chr_0004_pelica_g01_map01_lv006_sm1l6m1_001",
              "npc_gentleman_unionscholar_a_17_g01_map01_lv006_sm1l6m1_002",
              "npc_tpl_kidf_rfg_a_01_g01_map01_lv006_sm1l6m1_002"
            ]
          },
          "_uid": "10e0f954",
          "useCurrentScope": true
        },
        {
          "$type": "Beyond.Gameplay.Actions.SetFunctionAreaEnable, Gameplay.Beyond",
          "_ID": 6,
          "_nextID": 7,
          "_enable": {
            "constValue": true
          },
          "_functionAreaPtr": {
            "constValue": {
              "id": 3500150000
            }
          },
          "_uid": "268f2ef5",
          "useCurrentScope": true
        },
        {
          "$type": "Beyond.Gameplay.Actions.WaitForOneFrame, Gameplay.Beyond",
          "_ID": 7,
          "_nextID": 8,
          "_uid": "a268c534",
          "useCurrentScope": true
        },
        {
          "$type": "Beyond.Gameplay.Actions.CallServer, Gameplay.Beyond",
          "_ID": 8,
          "_eventName": {
            "constValue": "#981e4e14"
          },
          "_eventArgsPtr": {
            "constValue": {
              "key": "event_args"
            }
          },
          "_uid": "981e4e14",
          "useCurrentScope": true
        },
        {
          "$type": "Beyond.Gameplay.Actions.CreateMissionNpc, Gameplay.Beyond",
          "_ID": 18,
          "_nextID": 19,
          "_levelId": {
            "constValue": "map01_lv006"
          },
          "_npcIdList": {
            "constValue": [
              "npc_gentleman_unionscholar_a_17_g01_map01_lv006_sm1l6m1_002",
              "npc_tpl_kidf_rfg_a_01_g01_map01_lv006_sm1l6m1_002"
            ]
          },
          "_uid": "07353976",
          "useCurrentScope": true
        },
        {
          "$type": "Beyond.Gameplay.Actions.DestroyMissionNpc, Gameplay.Beyond",
          "_ID": 19,
          "_nextID": 20,
          "_levelId": {
            "constValue": "map01_lv006"
          },
          "_npcIdList": {
            "constValue": [
              "npc_chr_0004_pelica_g01_map01_lv006_sm1l6m1_001"
            ]
          },
          "_uid": "46e3aec4",
          "useCurrentScope": true
        },
        {
          "$type": "Beyond.Gameplay.Actions.SetFunctionAreaEnable, Gameplay.Beyond",
          "_ID": 20,
          "_nextID": 21,
          "_enable": {
            "constValue": false
          },
          "_functionAreaPtr": {
            "constValue": {
              "id": 3500150000
            }
          },
          "_uid": "8a799bf8",
          "useCurrentScope": true
        },
        {
          "$type": "Beyond.Gameplay.Actions.WaitForOneFrame, Gameplay.Beyond",
          "_ID": 21,
          "_nextID": 22,
          "_uid": "fd86c05d",
          "useCurrentScope": true
        },
        {
          "$type": "Beyond.Gameplay.Actions.CallServer, Gameplay.Beyond",
          "_ID": 22,
          "_eventName": {
            "constValue": "#d5a463e7"
          },
          "_eventArgsPtr": {
            "constValue": {
              "key": "event_args"
            }
          },
          "_uid": "d5a463e7",
          "useCurrentScope": true
        },
        {
          "$type": "Beyond.Gameplay.Actions.DestroyMissionNpc, Gameplay.Beyond",
          "_ID": 32,
          "_nextID": 33,
          "_levelId": {
            "constValue": "map01_lv006"
          },
          "_npcIdList": {
            "constValue": [
              "npc_gentleman_unionscholar_a_17_g01_map01_lv006_sm1l6m1_002",
              "npc_tpl_kidf_rfg_a_01_g01_map01_lv006_sm1l6m1_002"
            ]
          },
          "_uid": "41271240",
          "useCurrentScope": true
        },
        {
          "$type": "Beyond.Gameplay.Actions.CallServer, Gameplay.Beyond",
          "_ID": 33,
          "_eventName": {
            "constValue": "#321d8813"
          },
          "_eventArgsPtr": {
            "constValue": {
              "key": "event_args"
            }
          },
          "_uid": "321d8813",
          "useCurrentScope": true
        }
      ],
      "getterList": [
        {
          "$type": "Beyond.Gameplay.Actions.IntCompare, Gameplay.Beyond",
          "_ID": 11,
          "_comparer": {
            "constValue": "Equal"
          },
          "_valueA": {
            "paramSource": 300,
            "path": "StageCount",
            "constValue": 0
          },
          "_valueB": {
            "constValue": 1
          },
          "_uid": "dcea802e"
        },
        {
          "$type": "Beyond.Gameplay.Actions.IntCompare, Gameplay.Beyond",
          "_ID": 25,
          "_comparer": {
            "constValue": "Equal"
          },
          "_valueA": {
            "paramSource": 300,
            "path": "StageCount",
            "constValue": 0
          },
          "_valueB": {
            "constValue": 2
          },
          "_uid": "b9ed45b2"
        },
        {
          "$type": "Beyond.Gameplay.Actions.IntCompare, Gameplay.Beyond",
          "_ID": 36,
          "_comparer": {
            "constValue": "Equal"
          },
          "_valueA": {
            "paramSource": 300,
            "path": "StageCount",
            "constValue": 0
          },
          "_valueB": {
            "constValue": 3
          },
          "_uid": "3d27f9b7"
        }
      ]
    }
  },
  "resetModeWhenActive": "None",
  "resetModeWhenEnd": "None",
  "activeShapeList": [
    {
      "type": "SPHERE",
      "offset": {
        "x": 588.1,
        "y": 45.495785,
        "z": 240.2
      },
      "eulerAngles": {
        "x": 0.0,
        "y": 0.0,
        "z": 0.0
      },
      "size": {
        "x": 0.0,
        "y": 0.0,
        "z": 0.0
      },
      "radius": 125.0
    }
  ],
  "startShapeList": [
    {
      "type": "SPHERE",
      "offset": {
        "x": 588.1,
        "y": 45.495785,
        "z": 240.2
      },
      "eulerAngles": {
        "x": 0.0,
        "y": 0.0,
        "z": 0.0
      },
      "size": {
        "x": 10.0,
        "y": 10.0,
        "z": 10.0
      },
      "radius": 50.0
    }
  ],
  "properties": [
    {
      "key": "StageCount",
      "value": {
        "type": "Int",
        "valueArray": [
          {
            "valueBit64": 0,
            "valueString": ""
          }
        ]
      }
    },
    {
      "key": "lt:p:d8f1ab7d:8ac56e20",
      "value": {
        "type": "Int",
        "valueArray": [
          {
            "valueBit64": 0
          }
        ]
      }
    },
    {
      "key": "lt:p:a51a0d69:b7fe5952",
      "value": {
        "type": "Int",
        "valueArray": [
          {
            "valueBit64": 0
          }
        ]
      }
    },
    {
      "key": "lt:p:4e97ee42:429e69c5",
      "value": {
        "type": "Int",
        "valueArray": [
          {
            "valueBit64": 0
          }
        ]
      }
    },
    {
      "key": "lt:mp:d8f1ab7d:8ac56e20",
      "value": {
        "type": "Int",
        "valueArray": [
          {
            "valueBit64": 1
          }
        ]
      }
    },
    {
      "key": "lt:mp:a51a0d69:b7fe5952",
      "value": {
        "type": "Int",
        "valueArray": [
          {
            "valueBit64": 1
          }
        ]
      }
    },
    {
      "key": "lt:mp:4e97ee42:429e69c5",
      "value": {
        "type": "Int",
        "valueArray": [
          {
            "valueBit64": 1
          }
        ]
      }
    }
  ],
  "taskMap": {
    "4e97ee42": {
      "conditionDict": {
        "429e69c5": {
          "isMainObjective": true,
          "objectiveEnum": "Objective1",
          "condition": {
            "$type": "Beyond.Gameplay.CheckQuestState, Gameplay.Beyond",
            "_questId": {
              "constValue": "sm1l6m2_q#11"
            },
            "_comparer": {
              "constValue": "Equal"
            },
            "_targetQuestState": {
              "constValue": "Completed"
            },
            "uniqueId": "429e69c5",
            "detail": null,
            "parent": null,
            "useCurrentScope": false,
            "scopeMask": "Main",
            "useGraphScope": true
          }
        }
      },
      "taskType": "None",
      "needManualCheck": false,
      "canBeTracked": false
    },
    "a51a0d69": {
      "conditionDict": {
        "b7fe5952": {
          "isMainObjective": true,
          "objectiveEnum": "Objective1",
          "condition": {
            "$type": "Beyond.Gameplay.CheckQuestState, Gameplay.Beyond",
            "_questId": {
              "constValue": "sm1l6m1_q#3d2"
            },
            "_comparer": {
              "constValue": "Equal"
            },
            "_targetQuestState": {
              "constValue": "Completed"
            },
            "uniqueId": "b7fe5952",
            "detail": null,
            "parent": null,
            "useCurrentScope": false,
            "scopeMask": "Main",
            "useGraphScope": true
          }
        }
      },
      "taskType": "None",
      "needManualCheck": false,
      "canBeTracked": false
    },
    "d8f1ab7d": {
      "conditionDict": {
        "8ac56e20": {
          "isMainObjective": true,
          "objectiveEnum": "Objective1",
          "condition": {
            "$type": "Beyond.Gameplay.CheckQuestState, Gameplay.Beyond",
            "_questId": {
              "constValue": "sm1l6m1_q#6"
            },
            "_comparer": {
              "constValue": "Equal"
            },
            "_targetQuestState": {
              "constValue": "Completed"
            },
            "uniqueId": "8ac56e20",
            "detail": null,
            "parent": null,
            "useCurrentScope": false,
            "scopeMask": "Main",
            "useGraphScope": true
          }
        }
      },
      "taskType": "None",
      "needManualCheck": false,
      "canBeTracked": false
    }
  },
  "propertyIdToKeyMap": {
    "1": "StageCount",
    "2": "lt:p:d8f1ab7d:8ac56e20",
    "4": "lt:p:a51a0d69:b7fe5952",
    "6": "lt:p:4e97ee42:429e69c5",
    "1027": "lt:mp:d8f1ab7d:8ac56e20",
    "1029": "lt:mp:a51a0d69:b7fe5952",
    "1031": "lt:mp:4e97ee42:429e69c5"
  }
}